Workbook

Sheet Instructions
A1: Comparative Financial and Working Capital Analysis: HCLTech, TCS & Infosys
A3: Extracted_Data | B3: INPUT sheet. Type figures from HCLTech's consolidated annual reports (Rs crore) ; Screener for TCS & Infosys
A4: Calculation_Data | B4: Working capital, liquidity ratios, DSO / DIO / DPO and cash conversion cycle.
A5: YoY_Change | B5: Year-over-year absolute change, % change, change in ratios and Improved / Worsened signal.
A6: Peer Comparison | B6: Comparison of HCLTech, TCS & Infosys on liquidity ratios, DSO, DPO, cash conversion cycle and NWC as % of revenue.
A8: Colour legend
A9: Blue text | B9: Input - from annual report of FY25-26
A10: Black text | B10: Formula on the same sheet
A11: Green text | B11: Formula pulling from another sheet

Sheet Extracted_Data
A1: Extracted Data
A2: Amounts in Rs crore. Source: HCLTech Annual Reports.
B3: HCL Tech | D3: TCS | F3: Infosys
A4: Item (Rs crore) | B4: FY2025 | C4: FY2026 | D4: FY2025 | E4: FY2026 | F4: FY2025 | G4: FY2026
A5: Profit & Loss
A6: Revenue from operations | B6: 117055 | C6: 130144 | D6: 255324 | E6: 267021 | F6: 162990 | G6: 178650
A7: Operating costs (total expenses excl. finance cost) | B7: 95635 | C7: 107747 | D7: 193159 | E7: 200183 | F7: 128566 | G7: 141272
A8: Current assets (Balance Sheet)
A9: Trade receivables-Billed | B9: 19523 | C9: 23585 | D9: 50142 | E9: 57630 | F9: 31158 | G9: 35234
A10: Unbilled revenue | B10: 6319 | C10: 7956 | D10: 8904 | E10: 10084 | F10: 8183 | G10: 10064
A11: Inventories | B11: 133 | C11: 239 | D11: 21 | E11: 29
A12: Cash and cash equivalents | B12: 8245 | C12: 8265 | D12: 8342 | E12: 6417 | F12: 24455 | G12: 22201
A13: Other bank balances | B13: 13044 | C13: 15160 | D13: 7121 | E13: 6417
A14: Current investments | B14: 7473 | C14: 6960 | D14: 30689 | E14: 33770 | F14: 12482 | G14: 12950
A15: Total current assets (as reported) | B15: 62109 | C15: 70542 | D15: 123011 | E15: 135705 | F15: 97099 | G15: 103489
A16: Current liabilities (Balance Sheet)
A17: Trade payables – billed | B17: 3016 | C17: 3726 | D17: 7657 | E17: 7698 | F17: 4164 | G17: 4744
A18: Trade payables – unbilled | B18: 3209 | C18: 3980 | D18: 6252 | E18: 7110 | F18: 0 | G18: 0
A19: Short-term borrowings | B19: 2221 | C19: 122 | D19: 0 | E19: 0 | F19: 0 | G19: 0
A20: Total current liabilities (as reported) | B20: 28039 | C20: 31826 | D20: 53001 | E20: 60914 | F20: 42850 | G20: 52322
A22: Source: Annual Report 2025-2026 and Screener

Sheet Calculation_Data
A1: Calculation Data - Working Capital Metrics
A3: Assumption: 365 days used for DSO, DIO and DPO.
A4: Days in year | B4: 365
B5: HCL Tech | D5: TCS | E5: Infosys
A6: Metric | B6: FY2025 | C6: FY2026 | D6: FY2026 | E6: FY2026
A7: Total trade receivables (billed + unbilled) | B7: =Extracted_Data!B9+Extracted_Data!B10 -> 25842 | C7: =Extracted_Data!C9+Extracted_Data!C10 -> 31541 | D7: =SUM(Extracted_Data!E9:E10) -> 67714 | E7: =SUM(Extracted_Data!G9:G10) -> 45298
A8: Total trade payables (billed + unbilled) | B8: =Extracted_Data!B17+Extracted_Data!B18 -> 6225 | C8: =Extracted_Data!C17+Extracted_Data!C18 -> 7706 | D8: =SUM(Extracted_Data!E17:E18) -> 14808 | E8: =SUM(Extracted_Data!G17:G18) -> 4744
A9: Working capital (Rs crore)
A10: Net working capital | B10: =Extracted_Data!B15-Extracted_Data!B20 -> 34070 | C10: =Extracted_Data!C15-Extracted_Data!C20 -> 38716 | D10: =Extracted_Data!E15-Extracted_Data!E20 -> 74791 | E10: =Extracted_Data!G15-Extracted_Data!G20 -> 51167
A11: Operating working capital | B11: =Extracted_Data!B9+Extracted_Data!B10+Extracted_Data!B12-B8 -> 27862 | C11: =Extracted_Data!C9+Extracted_Data!C10+Extracted_Data!C11-C8 -> 24074 | D11: =SUM(Extracted_Data!E9:E11)-Calculation_Data!D8 -> 52935 | E11: =SUM(Extracted_Data!G9:G11)-E8 -> 40554
A12: Cash and liquid investments | B12: =SUM(Extracted_Data!B12:B14) -> 28762 | C12: =SUM(Extracted_Data!C12:C14) -> 30385 | D12: =SUM(Extracted_Data!E12:E14) -> 46604 | E12: =SUM(Extracted_Data!G12:G14) -> 35151
A13: Liquidity ratios (times)
A14: Current ratio | B14: =Extracted_Data!B15/Extracted_Data!B20 -> 2.2150933 | C14: =Extracted_Data!C15/Extracted_Data!C20 -> 2.2164897 | D14: =Extracted_Data!E15/Extracted_Data!E20 -> 2.227813 | E14: =Extracted_Data!G15/Extracted_Data!G20 -> 1.9779252
A15: Quick ratio | B15: =(Extracted_Data!B15-Extracted_Data!B11)/Extracted_Data!B20 -> 2.2103499 | C15: =(Extracted_Data!C15-Extracted_Data!C11)/Extracted_Data!C20 -> 2.2089801 | D15: =(Extracted_Data!E15-Extracted_Data!E11)/Extracted_Data!E20 -> 2.2273369 | E15: =(Extracted_Data!G15-Extracted_Data!G11)/Extracted_Data!G20 -> 1.9779252
A16: Cash ratio | B16: =B12/Extracted_Data!B20 -> 1.0257855 | C16: =C12/Extracted_Data!C20 -> 0.95472255 | D16: =D12/Extracted_Data!E20 -> 0.76507864 | E16: =E12/Extracted_Data!G20 -> 0.67182065
A17: Efficiency (days)
A18: DSO - Days Sales Outstanding | B18: =(B7/Extracted_Data!B6)*B4 -> 80.580325 | C18: =(C7/Extracted_Data!C6)*$B$4 -> 88.459437 | D18: =(D7/Extracted_Data!E6)*365 -> 92.560548 | E18: =(E7/Extracted_Data!G6)*365 -> 92.548391
A19: DIO - Days Inventory Outstanding | B19: =(Extracted_Data!B11/Extracted_Data!B7)*365 -> 0.50760705 | C19: =(Extracted_Data!C11/Extracted_Data!C7)*365 -> 0.80962811 | D19: =(Extracted_Data!E11/Extracted_Data!E7)*365 -> 0.052876618 | E19: =(Extracted_Data!G11/Extracted_Data!G7)*365 -> 0
A20: DPO - Days Payable Outstanding | B20: =(B8/Extracted_Data!B7)*365 -> 23.7583 | C20: =(C8/Extracted_Data!C7)*365 -> 26.104578 | D20: =(D8/Extracted_Data!E7)*365 -> 26.999895 | E20: =(E8/Extracted_Data!G7)*365 -> 12.256923
A21: Cash Conversion Cycle (days) | B21: =B18+B19-B20 -> 57.329633 | C21: =C18+C19-C20 -> 63.164487 | D21: =D18+D19-D20 -> 65.613529 | E21: =E18+E19-E20 -> 80.291468
A22: Other
A23: Net working capital as % of revenue | B23: =B10/Extracted_Data!B6 -> 0.29105976 | C23: =C10/Extracted_Data!C6 -> 0.29748586 | D23: =D10/Extracted_Data!E6 -> 0.28009407 | E23: =E10/Extracted_Data!G6 -> 0.28640918

Sheet YoY_Change
A1: Year-over-Year Change - HCL Technologies
A4: Item | B4: FY2026 | C4: Comment
A5: A. Absolute change (Rs crore)
A6: Revenue from operations | B6: =IFERROR(Extracted_Data!C6-Extracted_Data!B6,"") -> 13089
A7: Trade receivables | B7: =IFERROR(Extracted_Data!C9-Extracted_Data!B9,"") -> 4062
A8: Unbilled revenue | B8: =IFERROR(Extracted_Data!C10-Extracted_Data!B10,"") -> 1637
A9: Inventories | B9: =IFERROR(Extracted_Data!C11-Extracted_Data!B11,"") -> 106
A10: Cash and liquid investments | B10: =IFERROR(Calculation_Data!C12-Calculation_Data!B12,"") -> 1623
A11: Trade payables | B11: =Calculation_Data!C8-Calculation_Data!B8 -> 1481
A12: Total current assets | B12: =IFERROR(Extracted_Data!C15-Extracted_Data!B15,"") -> 8433
A13: Total current liabilities | B13: =IFERROR(Extracted_Data!C20-Extracted_Data!B20,"") -> 3787
A14: Net working capital | B14: =IFERROR(Calculation_Data!C10-Calculation_Data!B10,"") -> 4646
A15: Operating working capital | B15: =IFERROR(Calculation_Data!C11-Calculation_Data!B11,"") -> -3788
A16: B. Percentage change
A17: Revenue from operations | B17: =IFERROR((Extracted_Data!C6-Extracted_Data!B6)/ABS(Extracted_Data!B6),"") -> 0.11181923
A18: Trade receivables | B18: =IFERROR((Extracted_Data!C9-Extracted_Data!B9)/ABS(Extracted_Data!B9),"") -> 0.20806229
A19: Unbilled revenue | B19: =IFERROR((Extracted_Data!C10-Extracted_Data!B10)/ABS(Extracted_Data!B10),"") -> 0.25905998
A20: Inventories | B20: =IFERROR((Extracted_Data!C11-Extracted_Data!B11)/ABS(Extracted_Data!B11),"") -> 0.79699248
A21: Cash and liquid investments | B21: =IFERROR((Calculation_Data!C12-Calculation_Data!B12)/ABS(Calculation_Data!B12),"") -> 0.056428621
A22: Trade payables | B22: =IFERROR((Calculation_Data!C7-Calculation_Data!B7)/ABS(Calculation_Data!B7),"") -> 0.22053247
A23: Total current assets | B23: =IFERROR((Extracted_Data!C15-Extracted_Data!B15)/ABS(Extracted_Data!B15),"") -> 0.13577742
A24: Total current liabilities | B24: =IFERROR((Extracted_Data!C20-Extracted_Data!B20)/ABS(Extracted_Data!B20),"") -> 0.13506188
A25: Net working capital | B25: =IFERROR((Calculation_Data!C10-Calculation_Data!B10)/ABS(Calculation_Data!B10),"") -> 0.1363663
A26: Operating working capital | B26: =(Calculation_Data!C11-Calculation_Data!B11)/ABS(Calculation_Data!B11) -> -0.13595578
A27: C. Change in ratios and days
A28: Current ratio | B28: =IFERROR(Calculation_Data!C14-Calculation_Data!B14,"") -> 0.0013963996
A29: Quick ratio | B29: =IFERROR(Calculation_Data!C15-Calculation_Data!B15,"") -> -0.0013697906
A30: Cash ratio | B30: =IFERROR(Calculation_Data!C16-Calculation_Data!B16,"") -> -0.071062959
A31: DSO (days) | B31: =IFERROR(Calculation_Data!C18-Calculation_Data!B18,"") -> 7.8791118
A32: DIO (days) | B32: =IFERROR(Calculation_Data!C19-Calculation_Data!B19,"") -> 0.30202106
A33: DPO (days) | B33: =IFERROR(Calculation_Data!C20-Calculation_Data!B20,"") -> 2.3462785
A34: Cash conversion cycle (days) | B34: =IFERROR(Calculation_Data!C21-Calculation_Data!B21,"") -> 5.8348543
A35: NWC as % of revenue (points) | B35: =IFERROR(Calculation_Data!C23-Calculation_Data!B23,"") -> 0.0064261036
A36: D. Direction versus previous year
A37: Current ratio | B37: =IF(B28="","",IF(B28>0,"Improved",IF(B28<0,"Worsened","No change"))) -> Improved | C37: Higher is better (liquidity)
A38: Quick ratio | B38: =IF(B29="","",IF(B29>0,"Improved",IF(B29<0,"Worsened","No change"))) -> Worsened | C38: Higher is better (liquidity)
A39: DSO | B39: =IF(B31="","",IF(B31>0,"Worsened",IF(B31<0,"Improved","No change"))) -> Worsened | C39: Lower is better (faster collections)
A40: DPO | B40: =IF(B33="","",IF(B33>0,"Improved",IF(B33<0,"Worsened","No change"))) -> Improved | C40: Higher keeps cash longer; too high risks vendor strain
A41: Cash conversion cycle | B41: =IF(B34="","",IF(B34>0,"Worsened",IF(B34<0,"Improved","No change"))) -> Worsened | C41: Lower is better (cash tied up for fewer days)

Sheet Peer Comparison
A1: Peer Comparison of Working Capital Metrics: HCLTech vs TCS, Infosys (FY2026)
A3: Source: Annual Report 2025-26, Screener
A5: Company | B5: HCL Tech | C5: TCS | D5: Infosys
A6: Metric | B6: FY2026 | C6: FY2026 | D6: FY2026 | E6: Comment
A7: Current ratio | B7: =Calculation_Data!C14 -> 2.2164897 | C7: =Calculation_Data!D14 -> 2.227813 | D7: =Calculation_Data!E14 -> 1.9779252 | E7: HCLTech's current ratio (2.22x) is comparable to TCS (2.23x) and higher than Infosys (1.98x), indicating strong short-term liquidity. Its ratio remained stable compared with the previous year, while TCS and Infosys declined.
A8: Quick ratio | B8: =Calculation_Data!C15 -> 2.2089801 | C8: =Calculation_Data!D15 -> 2.2273369 | D8: =Calculation_Data!E15 -> 1.9779252 | E8: Almost identical to the current ratio at all three companies because inventory is negligible for IT services firms.
A9: DSO - Days Sales Outstanding | B9: =Calculation_Data!C18 -> 88.459437 | C9: =Calculation_Data!D18 -> 92.560548 | D9: =Calculation_Data!E18 -> 92.548391 | E9: HCLTech collects fastest (88 days vs about 92.5 for TCS and Infosys)
A10: DPO - Days Payable Outstanding | B10: =Calculation_Data!C20 -> 26.104578 | C10: =Calculation_Data!D20 -> 26.999895 | D10: =Calculation_Data!E20 -> 12.256923 | E10: HCLTech pays vendors in about 26 days, close to TCS (27) and well above Infosys (12). Infosys looks low partly because accrued expenses sit outside its trade payables, while HCLTech and TCS include them.
A11: Cash Conversion Cycle (days) | B11: =Calculation_Data!C21 -> 63.164487 | C11: =Calculation_Data!D21 -> 65.613529 | D11: =Calculation_Data!E21 -> 80.291468 | E11: HCLTech has the shortest cycle (63 days vs TCS 66 and Infosys 80). Infosys is overstated relative to peers because of the payables difference, so the HCLTech vs TCS gap of about 2.5 days is the reliable comparison.
A12: Net working capital as % of revenue | B12: =Calculation_Data!B23 -> 0.29105976 | C12: =Calculation_Data!D23 -> 0.28009407 | D12: =Calculation_Data!E23 -> 0.28640918 | E12: HCLTech 29.7%, TCS 28.0%, Infosys 28.6%. NWC includes cash and investments, so it partly reflects cash holdings. Operating working capital which favours HCLTech.
